qb_proof_of_concept/__init__.py
qb_proof_of_concept/__main__.py
qb_proof_of_concept-0.1.6.dist-info/METADATA
qb_proof_of_concept-0.1.6.dist-info/WHEEL
qb_proof_of_concept-0.1.6.dist-info/entry_points.txt
qb_proof_of_concept-0.1.6.dist-info/RECORD
