Metadata-Version: 2.4
Name: qb_proof_of_concept
Version: 0.1.6
Author-email: henceiusegentoo <61363222+henceiusegentoo@users.noreply.github.com>
Requires-Dist: qb-runtime
